django_history/__init__.py
django_history/apps.py
django_history/migrations/0001_initial.py
django_history/migrations/__init__.py
django_history/mixins/__init__.py
django_history/mixins/encoders.py
django_history/mixins/models.py
django_history/models/__init__.py
django_history/models/history.py
django_history/settings/__init__.py
django_history/settings/history.py
django_history/tasks/__init__.py
django_history/tasks/history.py
django_history/utils/__init__.py
django_history/utils/history.py
django_histories-1.0.2.dist-info/LICENSE
django_histories-1.0.2.dist-info/METADATA
django_histories-1.0.2.dist-info/WHEEL
django_histories-1.0.2.dist-info/top_level.txt
django_histories-1.0.2.dist-info/RECORD
