Metadata-Version: 2.1
Name: django-histories
Version: 1.0.2
Author: QuantumaStelata
Author-email: QuantumaStelata <quantumastelata@gmail.com>
Classifier: Programming Language :: Python :: 3
Classifier: License :: OSI Approved :: MIT License
Classifier: Operating System :: OS Independent
Requires-Python: >=3.7
License-File: LICENSE
